{"latitude":-6.3944475,"longitude":106.8213664,"timezone":"Asia\/Jakarta","currently":{"time":1594693316,"summary":"Humid and Mostly Cloudy","icon":"partly-cloudy-day","precipIntensity":0,"precipProbability":0,"temperature":82.91,"apparentTemperature":90.98,"dewPoint":75.9,"humidity":0.79,"pressure":1010.6,"windSpeed":2.6,"windGust":2.69,"windBearing":40,"cloudCover":0.68,"uvIndex":4,"visibility":10,"ozone":248.7},"hourly":{"summary":"Rain tomorrow morning and afternoon.","icon":"rain","data":[{"time":1594692000,"summary":"Humid and Mostly Cloudy","icon":"partly-cloudy-day","precipIntensity":0,"precipProbability":0,"temperature":81.73,"apparentTemperature":88.46,"dewPoint":75.47,"humidity":0.81,"pressure":1010.5,"windSpeed":2.7,"windGust":2.85,"windBearing":59,"cloudCover":0.61,"uvIndex":4,"visibility":10,"ozone":248.7},{"time":1594695600,"summary":"Humid and Mostly Cloudy","icon":"partly-cloudy-day","precipIntensity":0,"precipProbability":0,"temperature":84.7,"apparentTemperature":94.37,"dewPoint":76.37,"humidity":0.76,"pressure":1010.6,"windSpeed":2.68,"windGust":2.7,"windBearing":11,"cloudCover":0.78,"uvIndex":5,"visibility":10,"ozone":248.4},{"time":1594699200,"summary":"Humid and Mostly Cloudy","icon":"partly-cloudy-day","precipIntensity":0,"precipProbability":0,"temperature":86.67,"apparentTemperature":97.03,"dewPoint":75.98,"humidity":0.71,"pressure":1010,"windSpeed":3.7,"windGust":3.71,"windBearing":6,"cloudCover":0.82,"uvIndex":6,"visibility":10,"ozone":247.6},{"time":1594702800,"summary":"Humid and Mostly Cloudy","icon":"partly-cloudy-day","precipIntensity":0.0004,"precipProbability":0.02,"precipType":"rain","temperature":87.97,"apparentTemperature":98.32,"dewPoint":75.47,"humidity":0.67,"pressure":1009.2,"windSpeed":5.31,"windGust":5.31,"windBearing":19,"cloudCover":0.82,"uvIndex":6,"visibility":10,"ozone":246.6},{"time":1594706400,"summary":"Humid and Mostly Cloudy","icon":"partly-cloudy-day","precipIntensity":0.0012,"precipProbability":0.02,"precipType":"rain","temperature":88.62,"apparentTemperature":98.95,"dewPoint":75.24,"humidity":0.65,"pressure":1008.5,"windSpeed":6.83,"windGust":6.83,"windBearing":29,"cloudCover":0.81,"uvIndex":6,"visibility":10,"ozone":246},{"time":1594710000,"summary":"Humid and Mostly Cloudy","icon":"partly-cloudy-day","precipIntensity":0.0033,"precipProbability":0.05,"precipType":"rain","temperature":88.19,"apparentTemperature":98.58,"dewPoint":75.43,"humidity":0.66,"pressure":1008,"windSpeed":8.25,"windGust":8.25,"windBearing":27,"cloudCover":0.81,"uvIndex":5,"visibility":10,"ozone":246},{"time":1594713600,"summary":"Humid and Mostly Cloudy","icon":"partly-cloudy-day","precipIntensity":0.0077,"precipProbability":0.08,"precipType":"rain","temperature":87.31,"apparentTemperature":97.91,"dewPoint":75.94,"humidity":0.69,"pressure":1007.8,"windSpeed":9.49,"windGust":9.49,"windBearing":24,"cloudCover":0.8,"uvIndex":3,"visibility":10,"ozone":246.7},{"time":1594717200,"summary":"Humid and Mostly Cloudy","icon":"partly-cloudy-day","precipIntensity":0.0128,"precipProbability":0.09,"precipType":"rain","temperature":86.03,"apparentTemperature":95.97,"dewPoint":75.89,"humidity":0.72,"pressure":1007.9,"windSpeed":9.93,"windGust":9.93,"windBearing":28,"cloudCover":0.8,"uvIndex":2,"visibility":8.539,"ozone":247.3},{"time":1594720800,"summary":"Humid and Mostly Cloudy","icon":"partly-cloudy-day","precipIntensity":0.0167,"precipProbability":0.11,"precipType":"rain","temperature":84.4,"apparentTemperature":93.15,"dewPoint":75.61,"humidity":0.75,"pressure":1008.2,"windSpeed":9.01,"windGust":9.01,"windBearing":51,"cloudCover":0.81,"uvIndex":0,"visibility":7.559,"ozone":248},{"time":1594724400,"summary":"Humid and Mostly Cloudy","icon":"partly-cloudy-night","precipIntensity":0.0206,"precipProbability":0.14,"precipType":"rain","temperature":82.15,"apparentTemperature":88.53,"dewPoint":74.45,"humidity":0.78,"pressure":1008.9,"windSpeed":7.3,"windGust":7.68,"windBearing":78,"cloudCover":0.82,"uvIndex":0,"visibility":7.2,"ozone":248.8},{"time":1594728000,"summary":"Humid and Mostly Cloudy","icon":"partly-cloudy-night","precipIntensity":0.0218,"precipProbability":0.16,"precipType":"rain","temperature":80.39,"apparentTemperature":85.15,"dewPoint":73.83,"humidity":0.8,"pressure":1009.5,"windSpeed":5.8,"windGust":6.72,"windBearing":86,"cloudCover":0.81,"uvIndex":0,"visibility":7.724,"ozone":249.7},{"time":1594731600,"summary":"Humid and Mostly Cloudy","icon":"partly-cloudy-night","precipIntensity":0.0171,"precipProbability":0.15,"precipType":"rain","temperature":79.21,"apparentTemperature":82.84,"dewPoint":73.5,"humidity":0.83,"pressure":1010.2,"windSpeed":4.91,"windGust":6.14,"windBearing":98,"cloudCover":0.78,"uvIndex":0,"visibility":9.757,"ozone":250.9},{"time":1594735200,"summary":"Humid and Mostly Cloudy","icon":"partly-cloudy-night","precipIntensity":0.0102,"precipProbability":0.16,"precipType":"rain","temperature":78.45,"apparentTemperature":79.99,"dewPoint":73.59,"humidity":0.85,"pressure":1011,"windSpeed":4.24,"windGust":5.66,"windBearing":102,"cloudCover":0.75,"uvIndex":0,"visibility":10,"ozone":252.1},{"time":1594738800,"summary":"Humid and Mostly Cloudy","icon":"partly-cloudy-night","precipIntensity":0.0057,"precipProbability":0.16,"precipType":"rain","temperature":78,"apparentTemperature":79.58,"dewPoint":73.78,"humidity":0.87,"pressure":1011.4,"windSpeed":3.82,"windGust":5.28,"windBearing":106,"cloudCover":0.73,"uvIndex":0,"visibility":10,"ozone":252.7},{"time":1594742400,"summary":"Humid and Mostly Cloudy","icon":"partly-cloudy-night","precipIntensity":0.0033,"precipProbability":0.14,"precipType":"rain","temperature":77.69,"apparentTemperature":79.28,"dewPoint":73.71,"humidity":0.88,"pressure":1011.3,"windSpeed":3.72,"windGust":5.06,"windBearing":115,"cloudCover":0.76,"uvIndex":0,"visibility":10,"ozone":251.8},{"time":1594746000,"summary":"Humid and Mostly Cloudy","icon":"partly-cloudy-night","precipIntensity":0.0023,"precipProbability":0.12,"precipType":"rain","temperature":77.6,"apparentTemperature":79.2,"dewPoint":73.76,"humidity":0.88,"pressure":1010.7,"windSpeed":3.87,"windGust":4.95,"windBearing":125,"cloudCover":0.81,"uvIndex":0,"visibility":10,"ozone":250.1},{"time":1594749600,"summary":"Humid and Mostly Cloudy","icon":"partly-cloudy-night","precipIntensity":0.0024,"precipProbability":0.12,"precipType":"rain","temperature":77.49,"apparentTemperature":79.09,"dewPoint":73.76,"humidity":0.88,"pressure":1010.2,"windSpeed":3.98,"windGust":4.86,"windBearing":132,"cloudCover":0.86,"uvIndex":0,"visibility":10,"ozone":248.9},{"time":1594753200,"summary":"Humid and Overcast","icon":"cloudy","precipIntensity":0.004,"precipProbability":0.12,"precipType":"rain","temperature":77.04,"apparentTemperature":78.62,"dewPoint":73.54,"humidity":0.89,"pressure":1010,"windSpeed":3.93,"windGust":4.78,"windBearing":135,"cloudCover":0.91,"uvIndex":0,"visibility":10,"ozone":249.3},{"time":1594756800,"summary":"Humid and Overcast","icon":"cloudy","precipIntensity":0.0071,"precipProbability":0.07,"precipType":"rain","temperature":76.05,"apparentTemperature":77.58,"dewPoint":72.85,"humidity":0.9,"pressure":1009.5,"windSpeed":3.86,"windGust":4.73,"windBearing":136,"cloudCover":0.97,"uvIndex":0,"visibility":10,"ozone":250.4},{"time":1594760400,"summary":"Humid and Overcast","icon":"cloudy","precipIntensity":0.0092,"precipProbability":0.08,"precipType":"rain","temperature":75.18,"apparentTemperature":76.64,"dewPoint":72.12,"humidity":0.9,"pressure":1009.3,"windSpeed":3.81,"windGust":4.72,"windBearing":137,"cloudCover":1,"uvIndex":0,"visibility":10,"ozone":251},{"time":1594764000,"summary":"Overcast","icon":"cloudy","precipIntensity":0.0079,"precipProbability":0.14,"precipType":"rain","temperature":74.64,"apparentTemperature":76.03,"dewPoint":71.55,"humidity":0.9,"pressure":1009.5,"windSpeed":3.7,"windGust":4.48,"windBearing":144,"cloudCover":0.99,"uvIndex":0,"visibility":10,"ozone":250.8},{"time":1594767600,"summary":"Overcast","icon":"cloudy","precipIntensity":0.0075,"precipProbability":0.13,"precipType":"rain","temperature":74.67,"apparentTemperature":76.07,"dewPoint":71.55,"humidity":0.9,"pressure":1009.9,"windSpeed":3.61,"windGust":4.18,"windBearing":152,"cloudCover":0.97,"uvIndex":0,"visibility":10,"ozone":250.3},{"time":1594771200,"summary":"Humid and Overcast","icon":"cloudy","precipIntensity":0.0095,"precipProbability":0.13,"precipType":"rain","temperature":75.87,"apparentTemperature":77.36,"dewPoint":72.49,"humidity":0.89,"pressure":1010.2,"windSpeed":3.96,"windGust":4.26,"windBearing":148,"cloudCover":0.93,"uvIndex":0,"visibility":10,"ozone":249.8},{"time":1594774800,"summary":"Humid and Mostly Cloudy","icon":"partly-cloudy-day","precipIntensity":0.0102,"precipProbability":0.12,"precipType":"rain","temperature":78.59,"apparentTemperature":81.69,"dewPoint":73.81,"humidity":0.85,"pressure":1010.5,"windSpeed":5.19,"windGust":5.23,"windBearing":125,"cloudCover":0.81,"uvIndex":2,"visibility":10,"ozone":249.4},{"time":1594778400,"summary":"Humid and Mostly Cloudy","icon":"partly-cloudy-day","precipIntensity":0.0107,"precipProbability":0.11,"precipType":"rain","temperature":82.24,"apparentTemperature":89.18,"dewPoint":75.16,"humidity":0.79,"pressure":1010.8,"windSpeed":6.99,"windGust":6.99,"windBearing":93,"cloudCover":0.67,"uvIndex":4,"visibility":10,"ozone":249},{"time":1594782000,"summary":"Humid and Partly Cloudy","icon":"partly-cloudy-day","precipIntensity":0.0136,"precipProbability":0.11,"precipType":"rain","temperature":84.7,"apparentTemperature":93.51,"dewPoint":75.49,"humidity":0.74,"pressure":1010.7,"windSpeed":8.46,"windGust":8.46,"windBearing":68,"cloudCover":0.58,"uvIndex":6,"visibility":7.928,"ozone":248.8},{"time":1594785600,"summary":"Humid and Mostly Cloudy","icon":"partly-cloudy-day","precipIntensity":0.0221,"precipProbability":0.13,"precipType":"rain","temperature":86.15,"apparentTemperature":95.55,"dewPoint":75.32,"humidity":0.7,"pressure":1010.1,"windSpeed":9.12,"windGust":9.12,"windBearing":59,"cloudCover":0.6,"uvIndex":7,"visibility":6.068,"ozone":248.9},{"time":1594789200,"summary":"Humid and Mostly Cloudy","icon":"partly-cloudy-day","precipIntensity":0.0361,"precipProbability":0.18,"precipType":"rain","temperature":86.86,"apparentTemperature":96.42,"dewPoint":75.18,"humidity":0.68,"pressure":1009.1,"windSpeed":9.36,"windGust":9.38,"windBearing":56,"cloudCover":0.68,"uvIndex":7,"visibility":4.574,"ozone":249.1},{"time":1594792800,"summary":"Humid and Mostly Cloudy","icon":"partly-cloudy-day","precipIntensity":0.0456,"precipProbability":0.2,"precipType":"rain","temperature":87.49,"apparentTemperature":97.31,"dewPoint":75.17,"humidity":0.67,"pressure":1008.4,"windSpeed":9.46,"windGust":9.6,"windBearing":56,"cloudCover":0.76,"uvIndex":6,"visibility":4.23,"ozone":249.2},{"time":1594796400,"summary":"Humid and Mostly Cloudy","icon":"partly-cloudy-day","precipIntensity":0.0413,"precipProbability":0.18,"precipType":"rain","temperature":87.61,"apparentTemperature":97.37,"dewPoint":75.07,"humidity":0.66,"pressure":1007.9,"windSpeed":9.51,"windGust":9.58,"windBearing":60,"cloudCover":0.85,"uvIndex":5,"visibility":5.771,"ozone":249.2},{"time":1594800000,"summary":"Humid and Overcast","icon":"cloudy","precipIntensity":0.0306,"precipProbability":0.15,"precipType":"rain","temperature":87.62,"apparentTemperature":97.42,"dewPoint":75.1,"humidity":0.67,"pressure":1007.5,"windSpeed":9.4,"windGust":9.4,"windBearing":67,"cloudCover":0.94,"uvIndex":3,"visibility":8.462,"ozone":249},{"time":1594803600,"summary":"Humid and Overcast","icon":"cloudy","precipIntensity":0.0214,"precipProbability":0.14,"precipType":"rain","temperature":86.78,"apparentTemperature":95.62,"dewPoint":74.52,"humidity":0.67,"pressure":1007.5,"windSpeed":9.09,"windGust":9.09,"windBearing":72,"cloudCover":1,"uvIndex":1,"visibility":10,"ozone":249.1},{"time":1594807200,"summary":"Humid and Overcast","icon":"cloudy","precipIntensity":0.0148,"precipProbability":0.13,"precipType":"rain","temperature":85.21,"apparentTemperature":93.39,"dewPoint":74.54,"humidity":0.71,"pressure":1008,"windSpeed":8.49,"windGust":8.65,"windBearing":72,"cloudCover":1,"uvIndex":0,"visibility":10,"ozone":249.5},{"time":1594810800,"summary":"Humid and Overcast","icon":"cloudy","precipIntensity":0.0095,"precipProbability":0.13,"precipType":"rain","temperature":82.47,"apparentTemperature":88.48,"dewPoint":73.56,"humidity":0.75,"pressure":1008.7,"windSpeed":7.74,"windGust":8.48,"windBearing":69,"cloudCover":0.97,"uvIndex":0,"visibility":10,"ozone":250},{"time":1594814400,"summary":"Humid and Overcast","icon":"cloudy","precipIntensity":0.0058,"precipProbability":0.12,"precipType":"rain","temperature":80.5,"apparentTemperature":84.8,"dewPoint":72.56,"humidity":0.77,"pressure":1009.4,"windSpeed":7.04,"windGust":8.35,"windBearing":72,"cloudCover":0.96,"uvIndex":0,"visibility":10,"ozone":250.3},{"time":1594818000,"summary":"Humid and Overcast","icon":"cloudy","precipIntensity":0.0028,"precipProbability":0.1,"precipType":"rain","temperature":79.39,"apparentTemperature":82.82,"dewPoint":72.13,"humidity":0.79,"pressure":1009.9,"windSpeed":6.31,"windGust":8.08,"windBearing":84,"cloudCover":0.97,"uvIndex":0,"visibility":10,"ozone":250.3},{"time":1594821600,"summary":"Humid and Overcast","icon":"cloudy","precipIntensity":0.001,"precipProbability":0.07,"precipType":"rain","temperature":78.98,"apparentTemperature":82.11,"dewPoint":72.05,"humidity":0.79,"pressure":1010.1,"windSpeed":5.58,"windGust":7.72,"windBearing":100,"cloudCover":0.99,"uvIndex":0,"visibility":10,"ozone":250.2},{"time":1594825200,"summary":"Humid and Overcast","icon":"cloudy","precipIntensity":0.0004,"precipProbability":0.05,"precipType":"rain","temperature":78.67,"apparentTemperature":80,"dewPoint":72.01,"humidity":0.8,"pressure":1010.4,"windSpeed":4.99,"windGust":7.46,"windBearing":114,"cloudCover":1,"uvIndex":0,"visibility":10,"ozone":250.1},{"time":1594828800,"summary":"Humid and Overcast","icon":"cloudy","precipIntensity":0.0002,"precipProbability":0.04,"precipType":"rain","temperature":78.38,"apparentTemperature":79.73,"dewPoint":72.12,"humidity":0.81,"pressure":1010,"windSpeed":4.71,"windGust":7.49,"windBearing":128,"cloudCover":1,"uvIndex":0,"visibility":10,"ozone":250},{"time":1594832400,"summary":"Humid and Overcast","icon":"cloudy","precipIntensity":0,"precipProbability":0,"temperature":78.08,"apparentTemperature":79.45,"dewPoint":72.2,"humidity":0.82,"pressure":1009.4,"windSpeed":4.6,"windGust":7.62,"windBearing":142,"cloudCover":1,"uvIndex":0,"visibility":10,"ozone":250},{"time":1594836000,"summary":"Humid and Overcast","icon":"cloudy","precipIntensity":0,"precipProbability":0,"temperature":77.8,"apparentTemperature":79.18,"dewPoint":72.18,"humidity":0.83,"pressure":1009.1,"windSpeed":4.48,"windGust":7.61,"windBearing":155,"cloudCover":1,"uvIndex":0,"visibility":10,"ozone":250.1},{"time":1594839600,"summary":"Overcast","icon":"cloudy","precipIntensity":0.0004,"precipProbability":0.03,"precipType":"rain","temperature":76.99,"apparentTemperature":78.33,"dewPoint":71.7,"humidity":0.84,"pressure":1008.7,"windSpeed":4.21,"windGust":7.19,"windBearing":171,"cloudCover":1,"uvIndex":0,"visibility":10,"ozone":250.6},{"time":1594843200,"summary":"Overcast","icon":"cloudy","precipIntensity":0.0015,"precipProbability":0.04,"precipType":"rain","temperature":75.96,"apparentTemperature":77.22,"dewPoint":70.96,"humidity":0.85,"pressure":1008.4,"windSpeed":3.92,"windGust":6.61,"windBearing":188,"cloudCover":1,"uvIndex":0,"visibility":10,"ozone":251.4},{"time":1594846800,"summary":"Overcast","icon":"cloudy","precipIntensity":0.0026,"precipProbability":0.04,"precipType":"rain","temperature":75.34,"apparentTemperature":76.55,"dewPoint":70.33,"humidity":0.84,"pressure":1008.2,"windSpeed":3.82,"windGust":6.38,"windBearing":195,"cloudCover":1,"uvIndex":0,"visibility":10,"ozone":251.8},{"time":1594850400,"summary":"Overcast","icon":"cloudy","precipIntensity":0.0023,"precipProbability":0.04,"precipType":"rain","temperature":75.3,"apparentTemperature":76.45,"dewPoint":69.93,"humidity":0.83,"pressure":1008.5,"windSpeed":4.04,"windGust":6.74,"windBearing":189,"cloudCover":1,"uvIndex":0,"visibility":10,"ozone":251.3},{"time":1594854000,"summary":"Overcast","icon":"cloudy","precipIntensity":0.0014,"precipProbability":0.03,"precipType":"rain","temperature":75.62,"apparentTemperature":76.79,"dewPoint":70.15,"humidity":0.83,"pressure":1009,"windSpeed":4.45,"windGust":7.45,"windBearing":175,"cloudCover":0.99,"uvIndex":0,"visibility":10,"ozone":250.4},{"time":1594857600,"summary":"Overcast","icon":"cloudy","precipIntensity":0.0008,"precipProbability":0.03,"precipType":"rain","temperature":76.49,"apparentTemperature":77.73,"dewPoint":70.89,"humidity":0.83,"pressure":1009.4,"windSpeed":4.77,"windGust":8.14,"windBearing":157,"cloudCover":0.99,"uvIndex":0,"visibility":10,"ozone":249.7},{"time":1594861200,"summary":"Overcast","icon":"cloudy","precipIntensity":0.0006,"precipProbability":0.03,"precipType":"rain","temperature":78.07,"apparentTemperature":79.36,"dewPoint":71.62,"humidity":0.81,"pressure":1009.7,"windSpeed":4.84,"windGust":8.68,"windBearing":132,"cloudCover":0.99,"uvIndex":2,"visibility":10,"ozone":249.5},{"time":1594864800,"summary":"Humid and Overcast","icon":"cloudy","precipIntensity":0.0006,"precipProbability":0.02,"precipType":"rain","temperature":80.2,"apparentTemperature":84.35,"dewPoint":72.66,"humidity":0.78,"pressure":1009.9,"windSpeed":4.83,"windGust":9.19,"windBearing":102,"cloudCover":1,"uvIndex":3,"visibility":10,"ozone":249.5}]},"daily":{"summary":"Rain throughout the week.","icon":"rain","data":[{"time":1594659600,"summary":"Humid and mostly cloudy throughout the day.","icon":"rain","sunriseTime":1594681560,"sunsetTime":1594723980,"moonPhase":0.8,"precipIntensity":0.0051,"precipIntensityMax":0.022,"precipIntensityMaxTime":1594727220,"precipProbability":0.49,"precipType":"rain","temperatureHigh":89.12,"temperatureHighTime":1594706640,"temperatureLow":74.05,"temperatureLowTime":1594765980,"apparentTemperatureHigh":98.96,"apparentTemperatureHighTime":1594706700,"apparentTemperatureLow":75.93,"apparentTemperatureLowTime":1594765980,"dewPoint":74.22,"humidity":0.81,"pressure":1009.5,"windSpeed":5.14,"windGust":9.95,"windGustTime":1594716720,"windBearing":78,"cloudCover":0.59,"uvIndex":6,"uvIndexTime":1594703220,"visibility":9.615,"ozone":248.8,"temperatureMin":74.13,"temperatureMinTime":1594678800,"temperatureMax":89.12,"temperatureMaxTime":1594706640,"apparentTemperatureMin":76.05,"apparentTemperatureMinTime":1594679160,"apparentTemperatureMax":98.96,"apparentTemperatureMaxTime":1594706700},{"time":1594746000,"summary":"Rain in the morning and afternoon.","icon":"rain","sunriseTime":1594767960,"sunsetTime":1594810380,"moonPhase":0.83,"precipIntensity":0.0131,"precipIntensityMax":0.0458,"precipIntensityMaxTime":1594793280,"precipProbability":0.79,"precipType":"rain","temperatureHigh":88.19,"temperatureHighTime":1594798740,"temperatureLow":74.77,"temperatureLowTime":1594848720,"apparentTemperatureHigh":97.54,"apparentTemperatureHighTime":1594798860,"apparentTemperatureLow":76.43,"apparentTemperatureLowTime":1594849200,"dewPoint":73.53,"humidity":0.79,"pressure":1009.5,"windSpeed":6.36,"windGust":9.62,"windGustTime":1594794060,"windBearing":86,"cloudCover":0.89,"uvIndex":7,"uvIndexTime":1594787280,"visibility":9.051,"ozone":249.7,"temperatureMin":74.05,"temperatureMinTime":1594765980,"temperatureMax":88.19,"temperatureMaxTime":1594798740,"apparentTemperatureMin":75.93,"apparentTemperatureMinTime":1594765980,"apparentTemperatureMax":97.54,"apparentTemperatureMaxTime":1594798860},{"time":1594832400,"summary":"Humid and overcast throughout the day.","icon":"cloudy","sunriseTime":1594854360,"sunsetTime":1594896840,"moonPhase":0.86,"precipIntensity":0.0007,"precipIntensityMax":0.0026,"precipIntensityMaxTime":1594847520,"precipProbability":0.28,"precipType":"rain","temperatureHigh":88.62,"temperatureHighTime":1594881420,"temperatureLow":74.23,"temperatureLowTime":1594938900,"apparentTemperatureHigh":96.68,"apparentTemperatureHighTime":1594884360,"apparentTemperatureLow":75.84,"apparentTemperatureLowTime":1594938720,"dewPoint":72.63,"humidity":0.77,"pressure":1008.7,"windSpeed":5.33,"windGust":12.42,"windGustTime":1594878360,"windBearing":98,"cloudCover":0.96,"uvIndex":5,"uvIndexTime":1594875900,"visibility":10,"ozone":249.6,"temperatureMin":74.77,"temperatureMinTime":1594848720,"temperatureMax":88.62,"temperatureMaxTime":1594881420,"apparentTemperatureMin":76.43,"apparentTemperatureMinTime":1594849200,"apparentTemperatureMax":96.68,"apparentTemperatureMaxTime":1594884360},{"time":1594918800,"summary":"Humid throughout the day.","icon":"rain","sunriseTime":1594940760,"sunsetTime":1594983240,"moonPhase":0.89,"precipIntensity":0.0122,"precipIntensityMax":0.0457,"precipIntensityMaxTime":1594997760,"precipProbability":0.48,"precipType":"rain","temperatureHigh":89.88,"temperatureHighTime":1594967580,"temperatureLow":75.28,"temperatureLowTime":1595025480,"apparentTemperatureHigh":99.6,"apparentTemperatureHighTime":1594971900,"apparentTemperatureLow":77.34,"apparentTemperatureLowTime":1595025300,"dewPoint":73.55,"humidity":0.79,"pressure":1009.1,"windSpeed":4.62,"windGust":7.6,"windGustTime":1594973940,"windBearing":75,"cloudCover":0.46,"uvIndex":10,"uvIndexTime":1594962120,"visibility":9.924,"ozone":250,"temperatureMin":74.23,"temperatureMinTime":1594938900,"temperatureMax":89.88,"temperatureMaxTime":1594967580,"apparentTemperatureMin":75.84,"apparentTemperatureMinTime":1594938720,"apparentTemperatureMax":99.6,"apparentTemperatureMaxTime":1594971900},{"time":1595005200,"summary":"Humid and partly cloudy throughout the day.","icon":"rain","sunriseTime":1595027160,"sunsetTime":1595069640,"moonPhase":0.93,"precipIntensity":0.0038,"precipIntensityMax":0.0134,"precipIntensityMaxTime":1595005200,"precipProbability":0.39,"precipType":"rain","temperatureHigh":89.34,"temperatureHighTime":1595053860,"temperatureLow":72.63,"temperatureLowTime":1595112360,"apparentTemperatureHigh":97.72,"apparentTemperatureHighTime":1595058660,"apparentTemperatureLow":74.28,"apparentTemperatureLowTime":1595112060,"dewPoint":73.84,"humidity":0.8,"pressure":1009.3,"windSpeed":3.75,"windGust":7.61,"windGustTime":1595062500,"windBearing":63,"cloudCover":0.49,"uvIndex":9,"uvIndexTime":1595048580,"visibility":10,"ozone":251.9,"temperatureMin":75.28,"temperatureMinTime":1595025480,"temperatureMax":89.34,"temperatureMaxTime":1595053860,"apparentTemperatureMin":77.34,"apparentTemperatureMinTime":1595025300,"apparentTemperatureMax":97.72,"apparentTemperatureMaxTime":1595058660},{"time":1595091600,"summary":"Humid throughout the day.","icon":"clear-day","sunriseTime":1595113560,"sunsetTime":1595156040,"moonPhase":0.96,"precipIntensity":0.0008,"precipIntensityMax":0.0032,"precipIntensityMaxTime":1595161260,"precipProbability":0.21,"precipType":"rain","temperatureHigh":89.7,"temperatureHighTime":1595145360,"temperatureLow":72.03,"temperatureLowTime":1595197080,"apparentTemperatureHigh":95.53,"apparentTemperatureHighTime":1595145600,"apparentTemperatureLow":73.64,"apparentTemperatureLowTime":1595196960,"dewPoint":71.67,"humidity":0.76,"pressure":1008.7,"windSpeed":4.41,"windGust":9.52,"windGustTime":1595159220,"windBearing":1,"cloudCover":0.24,"uvIndex":10,"uvIndexTime":1595134800,"visibility":10,"ozone":252.2,"temperatureMin":72.63,"temperatureMinTime":1595112360,"temperatureMax":89.7,"temperatureMaxTime":1595145360,"apparentTemperatureMin":74.28,"apparentTemperatureMinTime":1595112060,"apparentTemperatureMax":95.53,"apparentTemperatureMaxTime":1595145600},{"time":1595178000,"summary":"Humid and partly cloudy throughout the day.","icon":"rain","sunriseTime":1595199960,"sunsetTime":1595242440,"moonPhase":1,"precipIntensity":0.0087,"precipIntensityMax":0.0379,"precipIntensityMaxTime":1595235840,"precipProbability":0.61,"precipType":"rain","temperatureHigh":88.29,"temperatureHighTime":1595226180,"temperatureLow":74.13,"temperatureLowTime":1595284260,"apparentTemperatureHigh":94.51,"apparentTemperatureHighTime":1595231400,"apparentTemperatureLow":75.84,"apparentTemperatureLowTime":1595283780,"dewPoint":71.61,"humidity":0.77,"pressure":1009.4,"windSpeed":4.74,"windGust":13.14,"windGustTime":1595236140,"windBearing":77,"cloudCover":0.54,"uvIndex":9,"uvIndexTime":1595221800,"visibility":9.751,"ozone":253.3,"temperatureMin":72.03,"temperatureMinTime":1595197080,"temperatureMax":88.29,"temperatureMaxTime":1595226180,"apparentTemperatureMin":73.64,"apparentTemperatureMinTime":1595196960,"apparentTemperatureMax":94.51,"apparentTemperatureMaxTime":1595231400},{"time":1595264400,"summary":"Rain in the evening.","icon":"rain","sunriseTime":1595286360,"sunsetTime":1595328840,"moonPhase":0.03,"precipIntensity":0.0129,"precipIntensityMax":0.0564,"precipIntensityMaxTime":1595334000,"precipProbability":0.66,"precipType":"rain","temperatureHigh":88.59,"temperatureHighTime":1595318280,"temperatureLow":73.24,"temperatureLowTime":1595371260,"apparentTemperatureHigh":95.48,"apparentTemperatureHighTime":1595320020,"apparentTemperatureLow":75.02,"apparentTemperatureLowTime":1595370960,"dewPoint":72.07,"humidity":0.76,"pressure":1009.6,"windSpeed":4,"windGust":7.11,"windGustTime":1595264400,"windBearing":110,"cloudCover":0.76,"uvIndex":5,"uvIndexTime":1595307900,"visibility":9.25,"ozone":255.2,"temperatureMin":74.13,"temperatureMinTime":1595284260,"temperatureMax":88.59,"temperatureMaxTime":1595318280,"apparentTemperatureMin":75.84,"apparentTemperatureMinTime":1595283780,"apparentTemperatureMax":95.48,"apparentTemperatureMaxTime":1595320020}]},"flags":{"sources":["cmc","gfs","icon","isd","madis"],"nearest-station":9.98,"units":"us"},"offset":7}